assertionengine/__init__.py
assertionengine/assertion_engine.py
assertionengine/assertion_formatter.py
assertionengine/py.typed
assertionengine/type_converter.py
robotframework_assertion_engine-3.1.3.dist-info/licenses/LICENSE
robotframework_assertion_engine-3.1.3.dist-info/METADATA
robotframework_assertion_engine-3.1.3.dist-info/WHEEL
robotframework_assertion_engine-3.1.3.dist-info/top_level.txt
robotframework_assertion_engine-3.1.3.dist-info/RECORD
