Metadata-Version: 2.4
Name: robotframework-assertion-engine
Version: 3.1.3
Summary: Generic way to create meaningful and easy to use assertions for the Robot Framework libraries.
Author-email: Tatu Aalto <aalto.tatu@gmail.com>
License-Expression: Apache-2.0
Project-URL: Homepage, https://github.com/MarketSquare/AssertionEngine
Project-URL: Issues, https://github.com/MarketSquare/AssertionEngine/issues
Project-URL: Changelog, https://github.com/MarketSquare/AssertionEngine/releases
Keywords: Robot Framework,Libraries,Assertions
Classifier: Programming Language :: Python :: 3
Classifier: Operating System :: OS Independent
Requires-Python: >=3.10
License-File: LICENSE
Requires-Dist: robotframework>=6.1.1
Requires-Dist: robotframework-pythonlibcore>=3.0.0
Dynamic: license-file
